ditti_boost/__init__.py
ditti_boost/authentication.py
ditti_boost/cli.py
ditti_boost/config.py
ditti_boost/menu.py
ditti_boost/reporting.py
ditti_boost/scripts.py
ditti_boost-1.0.1.dist-info/WHEEL
ditti_boost-1.0.1.dist-info/entry_points.txt
ditti_boost-1.0.1.dist-info/METADATA
ditti_boost-1.0.1.dist-info/RECORD
