Metadata-Version: 2.1
Name: ditti-boost
Version: 1.0.1
Summary: 
Author: alex paden
Author-email: padenalex0@gmail.com
Requires-Python: >=3.9,<3.11
Classifier: Programming Language :: Python :: 3
Classifier: Programming Language :: Python :: 3.9
Classifier: Programming Language :: Python :: 3.10
Requires-Dist: farcaster (>=0.7.7,<0.8.0)
